[
  {
    "title": "38AmbushAlley",
    "slug": "38ambushalley",
    "page_url": "https://www.romspedia.com/roms/action-max/38ambushalley",
    "image": "https://static.romspedia.com/webp/roms/38-ambush-alley-action-max-cover.webp",
    "rating": "N/A",
    "file_name": "38AmbushAlley.zip",
    "size": "unknown",
    "console": "Action Max",
    "category": "N/A",
    "region": "USA",
    "release_year": "1987",
    "downloads": "583",
    "download_url": "https://downloads.romspedia.com/roms/38AmbushAlley.zip"
  },
  {
    "title": "Blue Thunder",
    "slug": "blue-thunder",
    "page_url": "https://www.romspedia.com/roms/action-max/blue-thunder",
    "image": "https://static.romspedia.com/webp/roms/blue-thunder-actionmax-cover.webp",
    "rating": "N/A",
    "file_name": "BlueThunder.zip",
    "size": "unknown",
    "console": "Action Max",
    "category": "N/A",
    "region": "USA",
    "release_year": "1987",
    "downloads": "790",
    "download_url": "https://downloads.romspedia.com/roms/BlueThunder.zip"
  },
  {
    "title": "Hydrosub 2021",
    "slug": "hydrosub-2021",
    "page_url": "https://www.romspedia.com/roms/action-max/hydrosub-2021",
    "image": "https://static.romspedia.com/webp/roms/hydrosub2021-actionmax-cover.webp",
    "rating": "N/A",
    "file_name": "Hydrosub2021.zip",
    "size": "unknown",
    "console": "Action Max",
    "category": "N/A",
    "region": "USA",
    "release_year": "1987",
    "downloads": "451",
    "download_url": "https://downloads.romspedia.com/roms/Hydrosub2021.zip"
  },
  {
    "title": "PopsGhostly",
    "slug": "popsghostly",
    "page_url": "https://www.romspedia.com/roms/action-max/popsghostly",
    "image": "https://static.romspedia.com/webp/roms/popsghostly-actionmax-cover.webp",
    "rating": "N/A",
    "file_name": "PopsGhostly.zip",
    "size": "unknown",
    "console": "Action Max",
    "category": "N/A",
    "region": "USA",
    "release_year": "1987",
    "downloads": "502",
    "download_url": "https://downloads.romspedia.com/roms/PopsGhostly.zip"
  },
  {
    "title": "Sonic Fury",
    "slug": "sonic-fury",
    "page_url": "https://www.romspedia.com/roms/action-max/sonic-fury",
    "image": "https://static.romspedia.com/webp/roms/sonic-fury-actionmax-cover.webp",
    "rating": "N/A",
    "file_name": "SonicFury.zip",
    "size": "unknown",
    "console": "Action Max",
    "category": "N/A",
    "region": "USA",
    "release_year": "1987",
    "downloads": "675",
    "download_url": "https://downloads.romspedia.com/roms/SonicFury.zip"
  }
]