[
  {
    "title": "18 Wheeler American Pro Trucker",
    "slug": "18-wheeler-american-pro-trucker",
    "page_url": "https://www.romspedia.com/roms/sega-dreamcast/18-wheeler-american-pro-trucker",
    "image": "https://static.romspedia.com/webp/roms/18-wheeler-american-pro-trucker-dreamcast-cover.webp",
    "rating": "N/A",
    "file_name": "18 Wheeler - American Pro Trucker (USA).7z",
    "size": "unknown",
    "console": "Dreamcast",
    "category": "Vehicular combat",
    "region": "USA",
    "release_year": "2001",
    "downloads": "1635",
    "download_url": "https://downloads.romspedia.com/roms/18%20Wheeler%20-%20American%20Pro%20Trucker%20%28USA%29.7z"
  },
  {
    "title": "Capcom Vs. SNK",
    "slug": "capcom-vs-snk",
    "page_url": "https://www.romspedia.com/roms/sega-dreamcast/capcom-vs-snk",
    "image": "https://static.romspedia.com/webp/roms/capcom-vs-snk-dreamcast-cover.webp",
    "rating": "N/A",
    "file_name": "Capcom vs. SNK (USA).7z",
    "size": "unknown",
    "console": "Dreamcast",
    "category": "Fight",
    "region": "USA",
    "release_year": "2000",
    "downloads": "2207",
    "download_url": "https://downloads.romspedia.com/roms/Capcom%20vs.%20SNK%20%28USA%29.7z"
  },
  {
    "title": "Capcom vs. SNK 2 - Millionaire Fighting 2001 (JP)(EN)",
    "slug": "capcom-vs-snk-2-millionaire-fighting-2001-jp-en",
    "page_url": "https://www.romspedia.com/roms/sega-dreamcast/capcom-vs-snk-2-millionaire-fighting-2001-jp-en",
    "image": "https://static.romspedia.com/webp/roms/capcom-vs-snk-milenium-dreamcast-eu-cover.webp",
    "rating": "N/A",
    "file_name": "Capcom vs. SNK 2 - Millionaire Fighting 2001 v1.001 (2001)(Capcom)(NTSC)(JP)(en)[!].zip",
    "size": "unknown",
    "console": "Dreamcast",
    "category": "N/A",
    "region": "Europe",
    "release_year": "2001",
    "downloads": "11132",
    "download_url": "https://downloads.romspedia.com/roms/Capcom%20vs.%20SNK%202%20-%20Millionaire%20Fighting%202001%20v1.001%20%282001%29%28Capcom%29%28NTSC%29%28JP%29%28en%29%5B%21%5D.zip"
  },
  {
    "title": "Crazy Taxi",
    "slug": "crazy-taxi",
    "page_url": "https://www.romspedia.com/roms/sega-dreamcast/crazy-taxi",
    "image": "https://static.romspedia.com/webp/roms/crazy-taxi-sega-dreamcast-cover.webp",
    "rating": "N/A",
    "file_name": "Crazy Taxi (USA).7z",
    "size": "84.07MB",
    "console": "Dreamcast",
    "category": "Driving/Racing",
    "region": "USA",
    "release_year": "N/A",
    "downloads": "9101",
    "download_url": "https://downloads.romspedia.com/roms/Crazy Taxi (USA).7z"
  },
  {
    "title": "Crazy Taxi 2",
    "slug": "crazy-taxi-2",
    "page_url": "https://www.romspedia.com/roms/sega-dreamcast/crazy-taxi-2",
    "image": "https://static.romspedia.com/webp/roms/crazy-taxi-2-dreamcast-cover.webp",
    "rating": "N/A",
    "file_name": "Crazy Taxi 2 (USA).7z",
    "size": "unknown",
    "console": "Dreamcast",
    "category": "Driving/Racing",
    "region": "USA",
    "release_year": "2001",
    "downloads": "4244",
    "download_url": "https://downloads.romspedia.com/roms/Crazy%20Taxi%202%20%28USA%29.7z"
  },
  {
    "title": "Daytona USA",
    "slug": "daytona-usa",
    "page_url": "https://www.romspedia.com/roms/sega-dreamcast/daytona-usa",
    "image": "https://static.romspedia.com/webp/roms/daytona-usa-dreamcast-cover.webp",
    "rating": "N/A",
    "file_name": "Daytona USA (USA).7z",
    "size": "unknown",
    "console": "Dreamcast",
    "category": "Driving/Racing",
    "region": "USA",
    "release_year": "2001",
    "downloads": "4361",
    "download_url": "https://downloads.romspedia.com/roms/Daytona%20USA%20%28USA%29.7z"
  },
  {
    "title": "Dead Or Alive 2",
    "slug": "dead-or-alive-2",
    "page_url": "https://www.romspedia.com/roms/sega-dreamcast/dead-or-alive-2",
    "image": "https://static.romspedia.com/webp/roms/dead-or-alive-2-dreamcast-cover.webp",
    "rating": "N/A",
    "file_name": "Dead or Alive 2 (USA).7z",
    "size": "unknown",
    "console": "Dreamcast",
    "category": "Fight",
    "region": "USA",
    "release_year": "2000",
    "downloads": "3862",
    "download_url": "https://downloads.romspedia.com/roms/Dead%20or%20Alive%202%20%28USA%29.7z"
  },
  {
    "title": "Dino Crisis",
    "slug": "dino-crisis",
    "page_url": "https://www.romspedia.com/roms/sega-dreamcast/dino-crisis",
    "image": "https://static.romspedia.com/webp/roms/dino-crisis-dreamcast-cover.webp",
    "rating": "N/A",
    "file_name": "Dino Crisis (USA).7z",
    "size": "unknown",
    "console": "Dreamcast",
    "category": "Survival",
    "region": "USA",
    "release_year": "1999",
    "downloads": "1794",
    "download_url": "https://downloads.romspedia.com/roms/Dino%20Crisis%20%28USA%29.7z"
  },
  {
    "title": "Grand Theft Auto 2",
    "slug": "grand-theft-auto-2",
    "page_url": "https://www.romspedia.com/roms/sega-dreamcast/grand-theft-auto-2",
    "image": "https://static.romspedia.com/webp/roms/grand-theft-auto-2-sega-dreamcast-cover.webp",
    "rating": "N/A",
    "file_name": "Grand Theft Auto 2 (USA).7z",
    "size": "unknown",
    "console": "Dreamcast",
    "category": "Role-Playing",
    "region": "USA",
    "release_year": "1999",
    "downloads": "2384",
    "download_url": "https://downloads.romspedia.com/roms/Grand%20Theft%20Auto%202%20%28USA%29.7z"
  },
  {
    "title": "Guilty Gear X By Your Side (J)",
    "slug": "guilty-gear-x-by-your-side-j",
    "page_url": "https://www.romspedia.com/roms/sega-dreamcast/guilty-gear-x-by-your-side-j",
    "image": "https://static.romspedia.com/webp/roms/guilty-gear-x-by-your-side-dreamcast-cover-japan.webp",
    "rating": "N/A",
    "file_name": "Guilty Gear X - By Your Side (Japan) (Rev A) (10M) (En).7z",
    "size": "unknown",
    "console": "Dreamcast",
    "category": "Fighting",
    "region": "Japan",
    "release_year": "2000",
    "downloads": "1987",
    "download_url": "https://downloads.romspedia.com/roms/Guilty%20Gear%20X%20-%20By%20Your%20Side%20%28Japan%29%20%28Rev%20A%29%20%2810M%29%20%28En%29.7z"
  },
  {
    "title": "House Of The Dead 2 The",
    "slug": "house-of-the-dead-2-the",
    "page_url": "https://www.romspedia.com/roms/sega-dreamcast/house-of-the-dead-2-the",
    "image": "https://static.romspedia.com/webp/roms/house-of-the-dead-2-the-dreamcast-cover.webp",
    "rating": "N/A",
    "file_name": "House of the Dead 2, The (USA).7z",
    "size": "unknown",
    "console": "Dreamcast",
    "category": "Survival",
    "region": "USA",
    "release_year": "1999",
    "downloads": "5124",
    "download_url": "https://downloads.romspedia.com/roms/House%20of%20the%20Dead%202%2C%20The%20%28USA%29.7z"
  },
  {
    "title": "Ikaruga (J)",
    "slug": "ikaruga-j",
    "page_url": "https://www.romspedia.com/roms/sega-dreamcast/ikaruga-j",
    "image": "https://static.romspedia.com/webp/roms/ikaruga-dreamcast-cover.webp",
    "rating": "N/A",
    "file_name": "Ikaruga (Japan).7z",
    "size": "38.38MB",
    "console": "Dreamcast",
    "category": "Shoot'em Up",
    "region": "Japan",
    "release_year": "2001",
    "downloads": "1686",
    "download_url": "https://downloads.romspedia.com/roms/Ikaruga (Japan).7z"
  },
  {
    "title": "Jet Set Radio (E)",
    "slug": "jet-set-radio-e",
    "page_url": "https://www.romspedia.com/roms/sega-dreamcast/jet-set-radio-e",
    "image": "https://static.romspedia.com/webp/roms/jet-set-radio-dreamcast-europe.webp",
    "rating": "N/A",
    "file_name": "Jet Set Radio (Europe) (En,Fr,De,Es).7z",
    "size": "unknown",
    "console": "Dreamcast",
    "category": "Platform",
    "region": "Europe",
    "release_year": "2000",
    "downloads": "10526",
    "download_url": "https://downloads.romspedia.com/roms/Jet%20Set%20Radio%20%28Europe%29%20%28En%2CFr%2CDe%2CEs%29.7z"
  },
  {
    "title": "JoJo's Bizarre Adventure",
    "slug": "jojos-bizarre-adventure",
    "page_url": "https://www.romspedia.com/roms/sega-dreamcast/jojos-bizarre-adventure",
    "image": "https://static.romspedia.com/webp/roms/jojo-s-bizarre-adventure-dreamcast-cover.webp",
    "rating": "N/A",
    "file_name": "JoJos Bizarre Adventure (USA).7z",
    "size": "94.10MB",
    "console": "Dreamcast",
    "category": "Action",
    "region": "USA",
    "release_year": "1998",
    "downloads": "3968",
    "download_url": "https://downloads.romspedia.com/roms/JoJos Bizarre Adventure (USA).7z"
  },
  {
    "title": "King Of Fighters The Evolution",
    "slug": "king-of-fighters-the-evolution",
    "page_url": "https://www.romspedia.com/roms/sega-dreamcast/king-of-fighters-the-evolution",
    "image": "https://static.romspedia.com/webp/roms/king-of-fighters-the-evolution-dreamcast-cover.webp",
    "rating": "N/A",
    "file_name": "King of Fighters, The - Evolution (USA) (En,Ja,Es,Pt).7z",
    "size": "unknown",
    "console": "Dreamcast",
    "category": "Fight",
    "region": "USA",
    "release_year": "2000",
    "downloads": "1776",
    "download_url": "https://downloads.romspedia.com/roms/King%20of%20Fighters%2C%20The%20-%20Evolution%20%28USA%29%20%28En%2CJa%2CEs%2CPt%29.7z"
  },
  {
    "title": "Legacy Of Kain Soul Reaver",
    "slug": "legacy-of-kain-soul-reaver",
    "page_url": "https://www.romspedia.com/roms/sega-dreamcast/legacy-of-kain-soul-reaver",
    "image": "https://static.romspedia.com/webp/roms/legacy-of-kain-soul-reaver-sega-dreamcast-cover.webp",
    "rating": "N/A",
    "file_name": "Legacy of Kain - Soul Reaver (USA).7z",
    "size": "unknown",
    "console": "Dreamcast",
    "category": "Action",
    "region": "USA",
    "release_year": "1999",
    "downloads": "2561",
    "download_url": "https://downloads.romspedia.com/roms/Legacy%20of%20Kain%20-%20Soul%20Reaver%20%28USA%29.7z"
  },
  {
    "title": "Marvel Vs. Capcom Clash Of Super Heroes",
    "slug": "marvel-vs-capcom-clash-of-super-heroes",
    "page_url": "https://www.romspedia.com/roms/sega-dreamcast/marvel-vs-capcom-clash-of-super-heroes",
    "image": "https://static.romspedia.com/webp/roms/marvel-vs-capcom-clash-of-super-heroes-sega-dreamcast-cover.webp",
    "rating": "N/A",
    "file_name": "Marvel vs. Capcom - Clash of Super Heroes (USA).7z",
    "size": "unknown",
    "console": "Dreamcast",
    "category": "Fight",
    "region": "USA",
    "release_year": "1998",
    "downloads": "5963",
    "download_url": "https://downloads.romspedia.com/roms//Marvel%20vs.%20Capcom%20-%20Clash%20of%20Super%20Heroes%20%28USA%29.7z"
  },
  {
    "title": "Mortal Kombat Gold",
    "slug": "mortal-kombat-gold",
    "page_url": "https://www.romspedia.com/roms/sega-dreamcast/mortal-kombat-gold",
    "image": "https://static.romspedia.com/webp/roms/mortal-kombat-gold-dreamcast-cover.webp",
    "rating": "N/A",
    "file_name": "Mortal Kombat Gold (USA).7z",
    "size": "unknown",
    "console": "Dreamcast",
    "category": "Fight",
    "region": "USA",
    "release_year": "1999",
    "downloads": "6241",
    "download_url": "https://downloads.romspedia.com/roms/Mortal%20Kombat%20Gold%20%28USA%29.7z"
  },
  {
    "title": "MSR Metropolis Street Racer",
    "slug": "msr-metropolis-street-racer",
    "page_url": "https://www.romspedia.com/roms/sega-dreamcast/msr-metropolis-street-racer",
    "image": "https://static.romspedia.com/webp/roms/msr-metropolis-street-racer-dreamcast-thumb.webp",
    "rating": "N/A",
    "file_name": "MSR - Metropolis Street Racer (USA) (Rev. A).7z",
    "size": "unknown",
    "console": "Dreamcast",
    "category": "Driving/Racing",
    "region": "USA",
    "release_year": "2000",
    "downloads": "2436",
    "download_url": "https://downloads.romspedia.com/roms/MSR%20-%20Metropolis%20Street%20Racer%20%28USA%29%20%28Rev.%20A%29.7z"
  },
  {
    "title": "Power Stone",
    "slug": "power-stone",
    "page_url": "https://www.romspedia.com/roms/sega-dreamcast/power-stone",
    "image": "https://static.romspedia.com/webp/roms/power-stone-dreamcast-cover.webp",
    "rating": "N/A",
    "file_name": "Power Stone (USA).7z",
    "size": "unknown",
    "console": "Dreamcast",
    "category": "Fight",
    "region": "USA",
    "release_year": "1999",
    "downloads": "1875",
    "download_url": "https://downloads.romspedia.com/roms/Power%20Stone%20%28USA%29.7z"
  },
  {
    "title": "Power Stone 2",
    "slug": "power-stone-2",
    "page_url": "https://www.romspedia.com/roms/sega-dreamcast/power-stone-2",
    "image": "https://static.romspedia.com/webp/roms/power-stone-2-dreamcast-cover.webp",
    "rating": "N/A",
    "file_name": "Power Stone 2 (USA).7z",
    "size": "unknown",
    "console": "Dreamcast",
    "category": "Fight",
    "region": "USA",
    "release_year": "2000",
    "downloads": "2509",
    "download_url": "https://downloads.romspedia.com/roms/Power%20Stone%202%20%28USA%29.7z"
  },
  {
    "title": "Project Justice",
    "slug": "project-justice",
    "page_url": "https://www.romspedia.com/roms/sega-dreamcast/project-justice",
    "image": "https://static.romspedia.com/webp/roms/project-justice-dreamcast-cover.webp",
    "rating": "N/A",
    "file_name": "Project Justice (USA).7z",
    "size": "unknown",
    "console": "Dreamcast",
    "category": "Fight",
    "region": "USA",
    "release_year": "2001",
    "downloads": "1721",
    "download_url": "https://downloads.romspedia.com/roms/Project%20Justice%20%28USA%29.7z"
  },
  {
    "title": "Rayman 2 The Great Escape (E)",
    "slug": "rayman-2-the-great-escape-e",
    "page_url": "https://www.romspedia.com/roms/sega-dreamcast/rayman-2-the-great-escape-e",
    "image": "https://static.romspedia.com/webp/roms/rayman-2-the-great-escape-dreamcast-cover-europe.webp",
    "rating": "N/A",
    "file_name": "Rayman 2 - The Great Escape (Europe) (En,Fr,De,Es,It).7z",
    "size": "unknown",
    "console": "Dreamcast",
    "category": "Platform",
    "region": "Europe",
    "release_year": "1999",
    "downloads": "4334",
    "download_url": "https://downloads.romspedia.com/roms/Rayman%202%20-%20The%20Great%20Escape%20%28Europe%29%20%28En%2CFr%2CDe%2CEs%2CIt%29.7z"
  },
  {
    "title": "Ready 2 Rumble Boxing",
    "slug": "ready-2-rumble-boxing",
    "page_url": "https://www.romspedia.com/roms/sega-dreamcast/ready-2-rumble-boxing",
    "image": "https://static.romspedia.com/webp/roms/ready-2-rumble-boxing-dreamcast-cover.webp",
    "rating": "N/A",
    "file_name": "Ready 2 Rumble Boxing (USA).7z",
    "size": "unknown",
    "console": "Dreamcast",
    "category": "Fight",
    "region": "USA",
    "release_year": "1999",
    "downloads": "3507",
    "download_url": "https://downloads.romspedia.com/roms/Ready%202%20Rumble%20Boxing%20%28USA%29.7z"
  },
  {
    "title": "Resident Evil 2 - Disc #1",
    "slug": "resident-evil-2-disc-1",
    "page_url": "https://www.romspedia.com/roms/sega-dreamcast/resident-evil-2-disc-1",
    "image": "https://static.romspedia.com/webp/roms/resident-evil-2-sega-dreamcast-cover-disc-1.webp",
    "rating": "N/A",
    "file_name": "Resident Evil 2 (USA) (Disc 1).7z",
    "size": "unknown",
    "console": "Dreamcast",
    "category": "Survival",
    "region": "USA",
    "release_year": "1998",
    "downloads": "3214",
    "download_url": "https://downloads.romspedia.com/roms/Resident%20Evil%202%20%28USA%29%20%28Disc%201%29.7z"
  },
  {
    "title": "Resident Evil 2 - Disc #2",
    "slug": "resident-evil-2-disc-2",
    "page_url": "https://www.romspedia.com/roms/sega-dreamcast/resident-evil-2-disc-2",
    "image": "https://static.romspedia.com/webp/roms/resident-evil-2-disc-2-sega-dreamcast-cover.webp",
    "rating": "N/A",
    "file_name": "Resident Evil 2 (USA) (Disc 2).7z",
    "size": "unknown",
    "console": "Dreamcast",
    "category": "Survival",
    "region": "USA",
    "release_year": "1998",
    "downloads": "1850",
    "download_url": "https://downloads.romspedia.com/roms/Resident%20Evil%202%20%28USA%29%20%28Disc%202%29.7z"
  },
  {
    "title": "Resident Evil 3 Nemesis",
    "slug": "resident-evil-3-nemesis",
    "page_url": "https://www.romspedia.com/roms/sega-dreamcast/resident-evil-3-nemesis",
    "image": "https://static.romspedia.com/webp/roms/resident-evil-3-nemesis-dreamcast-cover.webp",
    "rating": "N/A",
    "file_name": "Resident Evil 3 - Nemesis (USA)1.7z",
    "size": "unknown",
    "console": "Dreamcast",
    "category": "Survival",
    "region": "USA",
    "release_year": "1999",
    "downloads": "3432",
    "download_url": "https://downloads.romspedia.com/roms/Resident%20Evil%203%20-%20Nemesis%20%28USA%291.7z"
  },
  {
    "title": "Resident Evil Code Veronica - Disc #1",
    "slug": "resident-evil-code-veronica-disc-1",
    "page_url": "https://www.romspedia.com/roms/sega-dreamcast/resident-evil-code-veronica-disc-1",
    "image": "https://static.romspedia.com/webp/roms/resident-evil-code-veronica-dreamcast-cover-disc-1.webp",
    "rating": "N/A",
    "file_name": "Resident Evil - Code - Veronica (USA) (Disc 1).7z",
    "size": "unknown",
    "console": "Dreamcast",
    "category": "Survival",
    "region": "USA",
    "release_year": "2000",
    "downloads": "6206",
    "download_url": "https://downloads.romspedia.com/roms/Resident%20Evil%20-%20Code%20-%20Veronica%20%28USA%29%20%28Disc%201%29.7z"
  },
  {
    "title": "Resident Evil Code Veronica - Disc #2",
    "slug": "resident-evil-code-veronica-disc-2",
    "page_url": "https://www.romspedia.com/roms/sega-dreamcast/resident-evil-code-veronica-disc-2",
    "image": "https://static.romspedia.com/webp/roms/resident-evil-code-veronica-dreamcast-cover-disc-2.webp",
    "rating": "N/A",
    "file_name": "Resident Evil - Code - Veronica (USA) (Disc 2).7z",
    "size": "unknown",
    "console": "Dreamcast",
    "category": "Survival",
    "region": "USA",
    "release_year": "2000",
    "downloads": "2897",
    "download_url": "https://downloads.romspedia.com/roms/Resident%20Evil%20-%20Code%20-%20Veronica%20%28USA%29%20%28Disc%202%29.7z"
  },
  {
    "title": "Sega GT",
    "slug": "sega-gt",
    "page_url": "https://www.romspedia.com/roms/sega-dreamcast/sega-gt",
    "image": "https://static.romspedia.com/webp/roms/sega-gt-dreamcast-cover.webp",
    "rating": "N/A",
    "file_name": "Sega GT (USA).7z",
    "size": "unknown",
    "console": "Dreamcast",
    "category": "Driving/Racing",
    "region": "USA",
    "release_year": "N/A",
    "downloads": "1672",
    "download_url": "https://downloads.romspedia.com/roms/Sega%20GT%20%28USA%29.7z"
  },
  {
    "title": "Sega Rally 2 Sega Rally Championship",
    "slug": "sega-rally-2-sega-rally-championship",
    "page_url": "https://www.romspedia.com/roms/sega-dreamcast/sega-rally-2-sega-rally-championship",
    "image": "https://static.romspedia.com/webp/roms/sega-rally-2-sega-rally-championship-dreamcast-cover.webp",
    "rating": "N/A",
    "file_name": "Sega Rally 2 - Sega Rally Championship (USA).7z",
    "size": "unknown",
    "console": "Dreamcast",
    "category": "Driving/Racing",
    "region": "USA",
    "release_year": "1999",
    "downloads": "6082",
    "download_url": "https://downloads.romspedia.com/roms/Sega%20Rally%202%20-%20Sega%20Rally%20Championship%20%28USA%29.7z"
  },
  {
    "title": "Shenmue",
    "slug": "shenmue",
    "page_url": "https://www.romspedia.com/roms/sega-dreamcast/shenmue",
    "image": "https://static.romspedia.com/webp/roms/shenmue-dreamcast-cover.webp",
    "rating": "N/A",
    "file_name": "Shenmue (USA) (Shenmue Passport).7z",
    "size": "unknown",
    "console": "Dreamcast",
    "category": "Role-Playing",
    "region": "USA",
    "release_year": "1999",
    "downloads": "3748",
    "download_url": "https://downloads.romspedia.com/roms/Shenmue%20%28USA%29%20%28Shenmue%20Passport%29.7z"
  },
  {
    "title": "Sonic Adventure 2 (E)",
    "slug": "sonic-adventure-2-eur",
    "page_url": "https://www.romspedia.com/roms/sega-dreamcast/sonic-adventure-2-eur",
    "image": "https://static.romspedia.com/webp/roms/sonic-adventure-2-sega-dreamcast-cover-europe.webp",
    "rating": "N/A",
    "file_name": "Sonic Adventure 2 (Europe) (En,Ja,Fr,De,Es).7z",
    "size": "unknown",
    "console": "Dreamcast",
    "category": "Platformer",
    "region": "Europe",
    "release_year": "2001",
    "downloads": "23022",
    "download_url": "https://downloads.romspedia.com/roms/Sonic%20Adventure%202%20%28Europe%29%20%28En%2CJa%2CFr%2CDe%2CEs%29.7z"
  },
  {
    "title": "Sonic Adventure 2 (J)",
    "slug": "sonic-adventure-2-jp",
    "page_url": "https://www.romspedia.com/roms/sega-dreamcast/sonic-adventure-2-jp",
    "image": "https://static.romspedia.com/webp/roms/sonic-adventure-2-sega-dreamcast-cover-japan.webp",
    "rating": "N/A",
    "file_name": "Sonic Adventure 2 (Japan) (En,Ja,Fr,De,Es).7z",
    "size": "unknown",
    "console": "Dreamcast",
    "category": "Platformer",
    "region": "Japan",
    "release_year": "2001",
    "downloads": "2588",
    "download_url": "https://downloads.romspedia.com/roms/Sonic%20Adventure%202%20%28Japan%29%20%28En%2CJa%2CFr%2CDe%2CEs%29.7z"
  },
  {
    "title": "Sonic Adventure (E)",
    "slug": "sonic-adventure-eur",
    "page_url": "https://www.romspedia.com/roms/sega-dreamcast/sonic-adventure-eur",
    "image": "https://static.romspedia.com/webp/roms/sonic-adventure-sega-dreamcast-cover-europe.webp",
    "rating": "N/A",
    "file_name": "Sonic Adventure (Europe) (En,Ja,Fr,De,Es).7z",
    "size": "unknown",
    "console": "Dreamcast",
    "category": "Platform",
    "region": "Europe",
    "release_year": "1998",
    "downloads": "5804",
    "download_url": "https://downloads.romspedia.com/roms/Sonic%20Adventure%20%28Europe%29%20%28En%2CJa%2CFr%2CDe%2CEs%29.7z"
  },
  {
    "title": "Sonic Adventure (J)",
    "slug": "sonic-adventure-jp",
    "page_url": "https://www.romspedia.com/roms/sega-dreamcast/sonic-adventure-jp",
    "image": "https://static.romspedia.com/webp/roms/sonic-adventure-sega-dreamcast-cover-japan.webp",
    "rating": "N/A",
    "file_name": "Sonic Adventure (Japan).7z",
    "size": "unknown",
    "console": "Dreamcast",
    "category": "Platform",
    "region": "Japan",
    "release_year": "1998",
    "downloads": "2492",
    "download_url": "https://downloads.romspedia.com/roms/Sonic%20Adventure%20%28Japan%29.7z"
  },
  {
    "title": "Sonic Adventure",
    "slug": "sonic-adventure-usa",
    "page_url": "https://www.romspedia.com/roms/sega-dreamcast/sonic-adventure-usa",
    "image": "https://static.romspedia.com/webp/roms/sonic-adventure-sega-dreamcast-cover.webp",
    "rating": "N/A",
    "file_name": "Sonic Adventure (USA) (En,Ja,Fr,De,Es).7z",
    "size": "unknown",
    "console": "Dreamcast",
    "category": "Platform",
    "region": "USA",
    "release_year": "1998",
    "downloads": "35632",
    "download_url": "https://downloads.romspedia.com/roms/Sonic%20Adventure%20%28USA%29%20%28En%2CJa%2CFr%2CDe%2CEs%29.7z"
  },
  {
    "title": "Soul Calibur",
    "slug": "soul-calibur",
    "page_url": "https://www.romspedia.com/roms/sega-dreamcast/soul-calibur",
    "image": "https://static.romspedia.com/webp/roms/dreamcast-soul-calibur.webp",
    "rating": "N/A",
    "file_name": "Soul Calibur (USA)[DCCM].7z",
    "size": "unknown",
    "console": "Dreamcast",
    "category": "Fighting",
    "region": "USA",
    "release_year": "1995",
    "downloads": "5836",
    "download_url": "https://downloads.romspedia.com/roms/Soul%20Calibur%20%28USA%29%5BDCCM%5D.7z"
  },
  {
    "title": "Spawn In The Demon's Hand",
    "slug": "spawn-in-the-demons-hand",
    "page_url": "https://www.romspedia.com/roms/sega-dreamcast/spawn-in-the-demons-hand",
    "image": "https://static.romspedia.com/webp/roms/spawn-in-the-demons-hand-dreamcast-cover.webp",
    "rating": "N/A",
    "file_name": "Spawn - In the Demons Hand (USA).7z",
    "size": "unknown",
    "console": "Dreamcast",
    "category": "Action",
    "region": "USA",
    "release_year": "2000",
    "downloads": "3072",
    "download_url": "https://downloads.romspedia.com/roms/Spawn%20-%20In%20the%20Demons%20Hand%20%28USA%29.7z"
  },
  {
    "title": "Star Wars Episode I Racer",
    "slug": "star-wars-episode-i-racer",
    "page_url": "https://www.romspedia.com/roms/sega-dreamcast/star-wars-episode-i-racer",
    "image": "https://static.romspedia.com/webp/roms/star-wars-episode-I-racer-dreamcast-cover.webp",
    "rating": "N/A",
    "file_name": "Star Wars - Episode I - Racer (USA).7z",
    "size": "unknown",
    "console": "Dreamcast",
    "category": "Driving/Racing",
    "region": "USA",
    "release_year": "2000",
    "downloads": "1855",
    "download_url": "https://downloads.romspedia.com/roms/Star%20Wars%20-%20Episode%20I%20-%20Racer%20%28USA%29.7z"
  },
  {
    "title": "Street Fighter Alpha 3",
    "slug": "street-fighter-alpha-3",
    "page_url": "https://www.romspedia.com/roms/sega-dreamcast/street-fighter-alpha-3",
    "image": "https://static.romspedia.com/webp/roms/street-fighter-alpha-3-sega-dreamcast-cover.webp",
    "rating": "N/A",
    "file_name": "Street Fighter Alpha 3 (USA).7z",
    "size": "unknown",
    "console": "Dreamcast",
    "category": "Fight",
    "region": "USA",
    "release_year": "1998",
    "downloads": "3189",
    "download_url": "https://downloads.romspedia.com/roms/Street%20Fighter%20Alpha%203%20%28USA%29.7z"
  },
  {
    "title": "Street Fighter III 3rd Strike",
    "slug": "street-fighter-iii-3rd-strike",
    "page_url": "https://www.romspedia.com/roms/sega-dreamcast/street-fighter-iii-3rd-strike",
    "image": "https://static.romspedia.com/webp/roms/street-fighter-III-3rd-strike-dreamcast-cover.webp",
    "rating": "N/A",
    "file_name": "Street Fighter III - 3rd Strike (USA).7z",
    "size": "unknown",
    "console": "Dreamcast",
    "category": "Fight",
    "region": "USA",
    "release_year": "1999",
    "downloads": "3817",
    "download_url": "https://downloads.romspedia.com/roms/Street%20Fighter%20III%20-%203rd%20Strike%20%28USA%29.7z"
  },
  {
    "title": "Street Fighter III Double Impact",
    "slug": "street-fighter-iii-double-impact",
    "page_url": "https://www.romspedia.com/roms/sega-dreamcast/street-fighter-iii-double-impact",
    "image": "https://static.romspedia.com/webp/roms/street-fighter-III-double-impact-dreamcast-cover.webp",
    "rating": "N/A",
    "file_name": "Street Fighter III - Double Impact (USA).7z",
    "size": "unknown",
    "console": "Dreamcast",
    "category": "Fight",
    "region": "USA",
    "release_year": "1999",
    "downloads": "1716",
    "download_url": "https://downloads.romspedia.com/roms/Street%20Fighter%20III%20-%20Double%20Impact%20%28USA%29.7z"
  },
  {
    "title": "Sword Of The Berserk Guts Rage",
    "slug": "sword-of-the-berserk-guts-rage",
    "page_url": "https://www.romspedia.com/roms/sega-dreamcast/sword-of-the-berserk-guts-rage",
    "image": "https://static.romspedia.com/webp/roms/sword-of-the-berserk-guts-rage-dreamcast-cover.webp",
    "rating": "N/A",
    "file_name": "Sword of the Berserk - Guts Rage (USA).7z",
    "size": "unknown",
    "console": "Dreamcast",
    "category": "Hack and slash",
    "region": "USA",
    "release_year": "2000",
    "downloads": "4087",
    "download_url": "https://downloads.romspedia.com/roms/Sword%20of%20the%20Berserk%20-%20Guts%20Rage%20%28USA%29.7z"
  },
  {
    "title": "Tokyo Xtreme Racer 2",
    "slug": "tokyo-xtreme-racer-2",
    "page_url": "https://www.romspedia.com/roms/sega-dreamcast/tokyo-xtreme-racer-2",
    "image": "https://static.romspedia.com/webp/roms/tokyo-xtreme-racer-2-dreamcast-cover.webp",
    "rating": "N/A",
    "file_name": "Tokyo Xtreme Racer 2 (USA).7z",
    "size": "unknown",
    "console": "Dreamcast",
    "category": "Driving/Racing",
    "region": "USA",
    "release_year": "2000",
    "downloads": "2520",
    "download_url": "https://downloads.romspedia.com/roms/Tokyo%20Xtreme%20Racer%202%20%28USA%29.7z"
  },
  {
    "title": "Tomb Raider The Last Revelation",
    "slug": "tomb-raider-the-last-revelation",
    "page_url": "https://www.romspedia.com/roms/sega-dreamcast/tomb-raider-the-last-revelation",
    "image": "https://static.romspedia.com/webp/roms/tomb-raider-the-last-revelation-dreamcast-cover.webp",
    "rating": "N/A",
    "file_name": "Tomb Raider - The Last Revelation (USA).7z",
    "size": "unknown",
    "console": "Dreamcast",
    "category": "Action",
    "region": "USA",
    "release_year": "2000",
    "downloads": "1798",
    "download_url": "https://downloads.romspedia.com/roms/Tomb%20Raider%20-%20The%20Last%20Revelation%20%28USA%29.7z"
  },
  {
    "title": "Tony Hawk's Pro Skater 2",
    "slug": "tony-hawks-pro-skater-2",
    "page_url": "https://www.romspedia.com/roms/sega-dreamcast/tony-hawks-pro-skater-2",
    "image": "https://static.romspedia.com/webp/roms/tony-hawks-pro-skater-2-dreamcast-cover.webp",
    "rating": "N/A",
    "file_name": "Tony Hawks Pro Skater 2 (USA).7z",
    "size": "unknown",
    "console": "Dreamcast",
    "category": "Sports",
    "region": "USA",
    "release_year": "2000",
    "downloads": "2221",
    "download_url": "https://downloads.romspedia.com/roms/Tony%20Hawks%20Pro%20Skater%202%20%28USA%29.7z"
  },
  {
    "title": "Virtua Cop 2 (J)",
    "slug": "virtua-cop-2-j",
    "page_url": "https://www.romspedia.com/roms/sega-dreamcast/virtua-cop-2-j",
    "image": "https://static.romspedia.com/webp/roms/virtua-cop-2-dreamcast-cover-japan.webp",
    "rating": "N/A",
    "file_name": "Virtua Cop 2 (Japan).7z",
    "size": "unknown",
    "console": "Dreamcast",
    "category": "Shoot'em Up",
    "region": "Japan",
    "release_year": "1995",
    "downloads": "1724",
    "download_url": "https://downloads.romspedia.com/roms/Virtua%20Cop%202%20%28Japan%29.7z"
  },
  {
    "title": "Virtua Striker 2 Ver. 2000.1 (J)",
    "slug": "virtua-striker-2-ver-2000-1-j",
    "page_url": "https://www.romspedia.com/roms/sega-dreamcast/virtua-striker-2-ver-2000-1-j",
    "image": "https://static.romspedia.com/webp/roms/virtua-striker-2-ver-2000-1-dreamcast-cover-japan.webp",
    "rating": "N/A",
    "file_name": "Virtua Striker 2 Ver. 2000.1 (Japan) (En,Ja,Fr,De,Es).7z",
    "size": "57.29MB",
    "console": "Dreamcast",
    "category": "Sports",
    "region": "Japan",
    "release_year": "1999",
    "downloads": "2158",
    "download_url": "https://downloads.romspedia.com/roms/Virtua Striker 2 Ver. 2000.1 (Japan) (En,Ja,Fr,De,Es).7z"
  },
  {
    "title": "Virtua Tennis 2 Sega Professional Tennis (E)",
    "slug": "virtua-tennis-2-sega-professional-tennis-e",
    "page_url": "https://www.romspedia.com/roms/sega-dreamcast/virtua-tennis-2-sega-professional-tennis-e",
    "image": "https://static.romspedia.com/webp/roms/virtua-tennis-2-sega-professional-tennis-dreamcast-cover-europe.webp",
    "rating": "N/A",
    "file_name": "Virtua Tennis 2 - Sega Professional Tennis (Europe) (En,Fr,De,Es).7z",
    "size": "unknown",
    "console": "Dreamcast",
    "category": "Sports",
    "region": "Europe",
    "release_year": "2001",
    "downloads": "5628",
    "download_url": "https://downloads.romspedia.com/roms/Virtua%20Tennis%202%20-%20Sega%20Professional%20Tennis%20%28Europe%29%20%28En%2CFr%2CDe%2CEs%29.7z"
  },
  {
    "title": "AirForce Delta",
    "slug": "airforce-delta",
    "page_url": "https://www.romspedia.com/roms/sega-dreamcast/airforce-delta",
    "image": "https://static.romspedia.com/webp/roms/airforce-delta-dreamcast-cover.webp",
    "rating": "N/A",
    "file_name": "AirForce Delta (USA).7z",
    "size": "unknown",
    "console": "Dreamcast",
    "category": "Simulation",
    "region": "USA",
    "release_year": "1999",
    "downloads": "891",
    "download_url": "https://downloads.romspedia.com/roms/AirForce%20Delta%20%28USA%29.7z"
  },
  {
    "title": "Alone In The Dark The New Nightmare - Disc #1",
    "slug": "alone-in-the-dark-the-new-nightmare-disc-1",
    "page_url": "https://www.romspedia.com/roms/sega-dreamcast/alone-in-the-dark-the-new-nightmare-disc-1",
    "image": "https://static.romspedia.com/webp/roms/alone-in-the-dark-the-new-nightmare-dreamcast-cover-disc-1.webp",
    "rating": "N/A",
    "file_name": "Alone in the Dark - The New Nightmare (USA) (Disc 1).7z",
    "size": "unknown",
    "console": "Dreamcast",
    "category": "Action",
    "region": "USA",
    "release_year": "2001",
    "downloads": "1269",
    "download_url": "https://downloads.romspedia.com/roms/Alone%20in%20the%20Dark%20-%20The%20New%20Nightmare%20%28USA%29%20%28Disc%201%29.7z"
  },
  {
    "title": "Blue Stinger",
    "slug": "blue-stinger",
    "page_url": "https://www.romspedia.com/roms/sega-dreamcast/blue-stinger",
    "image": "https://static.romspedia.com/webp/roms/blue-stinger-dreamcast-cover.webp",
    "rating": "N/A",
    "file_name": "Blue Stinger (USA).7z",
    "size": "unknown",
    "console": "Dreamcast",
    "category": "Action",
    "region": "USA",
    "release_year": "1999",
    "downloads": "962",
    "download_url": "https://downloads.romspedia.com/roms/Blue%20Stinger%20%28USA%29.7z"
  },
  {
    "title": "Bomberman Online",
    "slug": "bomberman-online",
    "page_url": "https://www.romspedia.com/roms/sega-dreamcast/bomberman-online",
    "image": "https://static.romspedia.com/webp/roms/bomberman-online-dreamcast-cover.webp",
    "rating": "N/A",
    "file_name": "Bomberman Online (USA).7z",
    "size": "unknown",
    "console": "Dreamcast",
    "category": "Action",
    "region": "USA",
    "release_year": "2001",
    "downloads": "896",
    "download_url": "https://downloads.romspedia.com/roms/Bomberman%20Online%20%28USA%29.7z"
  },
  {
    "title": "Cannon Spike",
    "slug": "cannon-spike",
    "page_url": "https://www.romspedia.com/roms/sega-dreamcast/cannon-spike",
    "image": "https://static.romspedia.com/webp/roms/cannon-spike-dreamcast-cover.webp",
    "rating": "N/A",
    "file_name": "Cannon Spike (USA).7z",
    "size": "unknown",
    "console": "Dreamcast",
    "category": "Shoot'em Up",
    "region": "USA",
    "release_year": "2000",
    "downloads": "1099",
    "download_url": "https://downloads.romspedia.com/roms/Cannon%20Spike%20%28USA%29.7z"
  },
  {
    "title": "Capcom vs. SNK 2: Millionaire Fighting 2001 (Japan)",
    "slug": "capcom-vs-snk-2-millionaire-fighting-2001-japan",
    "page_url": "https://www.romspedia.com/roms/sega-dreamcast/capcom-vs-snk-2-millionaire-fighting-2001-japan",
    "image": "https://static.romspedia.com/webp/roms/capcom-vs-snk-milenium-dreamcast-japan-cover.webp",
    "rating": "N/A",
    "file_name": "Capcom vs. SNK 2 - Millionaire Fighting 2001 (JP)[DCCM].zip",
    "size": "unknown",
    "console": "Dreamcast",
    "category": "N/A",
    "region": "Japan",
    "release_year": "2001",
    "downloads": "831",
    "download_url": "https://downloads.romspedia.com/roms/Capcom%20vs.%20SNK%202%20-%20Millionaire%20Fighting%202001%20%28JP%29%5BDCCM%5D.zip"
  },
  {
    "title": "Capcom Vs. SNK Millennium Fight 2000 (J)",
    "slug": "capcom-vs-snk-millennium-fight-2000-j",
    "page_url": "https://www.romspedia.com/roms/sega-dreamcast/capcom-vs-snk-millennium-fight-2000-j",
    "image": "https://static.romspedia.com/webp/roms/capcom-vs-snk-millennium-fight-2000-dreamcast-cover.webp",
    "rating": "N/A",
    "file_name": "Capcom vs. SNK - Millennium Fight 2000 (Japan).7z",
    "size": "unknown",
    "console": "Dreamcast",
    "category": "Fight",
    "region": "Japan",
    "release_year": "2000",
    "downloads": "917",
    "download_url": "https://downloads.romspedia.com/roms/Capcom%20vs.%20SNK%20-%20Millennium%20Fight%202000%20%28Japan%29.7z"
  },
  {
    "title": "Dynamite Cop",
    "slug": "dynamite-cop",
    "page_url": "https://www.romspedia.com/roms/sega-dreamcast/dynamite-cop",
    "image": "https://static.romspedia.com/webp/roms/dynamite-cop-dreamcast-cover.webp",
    "rating": "N/A",
    "file_name": "Dynamite Cop! (USA).7z",
    "size": "unknown",
    "console": "Dreamcast",
    "category": "Beat 'em up",
    "region": "USA",
    "release_year": "1999",
    "downloads": "1630",
    "download_url": "https://downloads.romspedia.com/roms/Dynamite%20Cop%21%20%28USA%29.7z"
  },
  {
    "title": "Ecco The Dolphin Defender Of The Future",
    "slug": "ecco-the-dolphin-defender-of-the-future",
    "page_url": "https://www.romspedia.com/roms/sega-dreamcast/ecco-the-dolphin-defender-of-the-future",
    "image": "https://static.romspedia.com/webp/roms/ecco-the-dolphin-defender-of-the-future-dreamcast-cover.webp",
    "rating": "N/A",
    "file_name": "Ecco the Dolphin - Defender of the Future (USA) (En,Fr,De,Es).7z",
    "size": "unknown",
    "console": "Dreamcast",
    "category": "Adventure",
    "region": "USA",
    "release_year": "2000",
    "downloads": "1359",
    "download_url": "https://downloads.romspedia.com/roms/Ecco%20the%20Dolphin%20-%20Defender%20of%20the%20Future%20%28USA%29%20%28En%2CFr%2CDe%2CEs%29.7z"
  },
  {
    "title": "Expendable",
    "slug": "expendable",
    "page_url": "https://www.romspedia.com/roms/sega-dreamcast/expendable",
    "image": "https://static.romspedia.com/webp/roms/expendable-dreamcast-cover.webp",
    "rating": "N/A",
    "file_name": "Expendable (USA) (En,Fr,De,Es,It).7z",
    "size": "unknown",
    "console": "Dreamcast",
    "category": "Run and gun",
    "region": "USA",
    "release_year": "1999",
    "downloads": "827",
    "download_url": "https://downloads.romspedia.com/roms/Expendable%20%28USA%29%20%28En%2CFr%2CDe%2CEs%2CIt%29.7z"
  },
  {
    "title": "Fatal Fury Mark Of The Wolves",
    "slug": "fatal-fury-mark-of-the-wolves",
    "page_url": "https://www.romspedia.com/roms/sega-dreamcast/fatal-fury-mark-of-the-wolves",
    "image": "https://static.romspedia.com/webp/roms/fatal-fury-mark-of-the-wolvies-dreamcast-cover.webp",
    "rating": "N/A",
    "file_name": "Fatal Fury - Mark of the Wolves (USA).7z",
    "size": "unknown",
    "console": "Dreamcast",
    "category": "Fight",
    "region": "USA",
    "release_year": "2001",
    "downloads": "1363",
    "download_url": "https://downloads.romspedia.com/roms/Fatal%20Fury%20-%20Mark%20of%20the%20Wolves%20%28USA%29.7z"
  },
  {
    "title": "Fighting Force 2 (E)",
    "slug": "fighting-force-2-e",
    "page_url": "https://www.romspedia.com/roms/sega-dreamcast/fighting-force-2-e",
    "image": "https://static.romspedia.com/webp/roms/fighting-force-2-dreamcast-cover-europe.webp",
    "rating": "N/A",
    "file_name": "Fighting Force 2 (Europe) (En,Fr).7z",
    "size": "unknown",
    "console": "Dreamcast",
    "category": "Beat 'em up",
    "region": "Europe",
    "release_year": "2000",
    "downloads": "1252",
    "download_url": "https://downloads.romspedia.com/roms/Fighting%20Force%202%20%28Europe%29%20%28En%2CFr%29.7z"
  },
  {
    "title": "Gauntlet Legends",
    "slug": "gauntlet-legends",
    "page_url": "https://www.romspedia.com/roms/sega-dreamcast/gauntlet-legends",
    "image": "https://static.romspedia.com/webp/roms/gauntlet-legends-sega-dreamcast-cover.webp",
    "rating": "N/A",
    "file_name": "Gauntlet Legends (USA).7z",
    "size": "unknown",
    "console": "Dreamcast",
    "category": "Hack and slash",
    "region": "USA",
    "release_year": "1998",
    "downloads": "1123",
    "download_url": "https://downloads.romspedia.com/roms/Gauntlet%20Legends%20%28USA%29.7z"
  },
  {
    "title": "GigaWing 2",
    "slug": "gigawing-2",
    "page_url": "https://www.romspedia.com/roms/sega-dreamcast/gigawing-2",
    "image": "https://static.romspedia.com/webp/roms/gigawings-2-dreamcast-cover.webp",
    "rating": "N/A",
    "file_name": "GigaWing 2 (USA).7z",
    "size": "unknown",
    "console": "Dreamcast",
    "category": "Simulation",
    "region": "USA",
    "release_year": "2001",
    "downloads": "999",
    "download_url": "https://downloads.romspedia.com/roms/GigaWing%202%20%28USA%29.7z"
  },
  {
    "title": "Gundam Side Story Rise From The Ashes",
    "slug": "gundam-side-story-rise-from-the-ashes",
    "page_url": "https://www.romspedia.com/roms/sega-dreamcast/gundam-side-story-rise-from-the-ashes",
    "image": "https://static.romspedia.com/webp/roms/gundam-side-story-rise-from-the-ashes-dreamcast-cover.webp",
    "rating": "N/A",
    "file_name": "Gundam Side Story 0079 - Rise from the Ashes (USA).7z",
    "size": "unknown",
    "console": "Dreamcast",
    "category": "Action",
    "region": "USA",
    "release_year": "1999",
    "downloads": "981",
    "download_url": "https://downloads.romspedia.com/roms/Gundam%20Side%20Story%200079%20-%20Rise%20from%20the%20Ashes%20%28USA%29.7z"
  },
  {
    "title": "GunLord",
    "slug": "gunlord",
    "page_url": "https://www.romspedia.com/roms/sega-dreamcast/gunlord",
    "image": "https://static.romspedia.com/webp/roms/gunlord-dreamcast-cover.webp",
    "rating": "N/A",
    "file_name": "Gunlord [NGDEV.TEAM].zip",
    "size": "unknown",
    "console": "Dreamcast",
    "category": "N/A",
    "region": "USA",
    "release_year": "2012",
    "downloads": "1617",
    "download_url": "https://downloads.romspedia.com/roms/Gunlord%20%5BNGDEV.TEAM%5D.zip"
  },
  {
    "title": "House Of The Dead 2 The (J)",
    "slug": "house-of-the-dead-2-the-j",
    "page_url": "https://www.romspedia.com/roms/sega-dreamcast/house-of-the-dead-2-the-j",
    "image": "https://static.romspedia.com/webp/roms/house-of-the-dead-2-the-dreamcast-cover-japan.webp",
    "rating": "N/A",
    "file_name": "House of the Dead 2, The (Japan).7z",
    "size": "unknown",
    "console": "Dreamcast",
    "category": "Survival",
    "region": "Japan",
    "release_year": "1999",
    "downloads": "828",
    "download_url": "https://downloads.romspedia.com/roms/House%20of%20the%20Dead%202%2C%20The%20%28Japan%29.7z"
  },
  {
    "title": "Hydro Thunder",
    "slug": "hydro-thunder",
    "page_url": "https://www.romspedia.com/roms/sega-dreamcast/hydro-thunder",
    "image": "https://static.romspedia.com/webp/roms/hydro-thunder-dreamcast-cover.webp",
    "rating": "N/A",
    "file_name": "Hydro Thunder (USA) (Rev A).7z",
    "size": "unknown",
    "console": "Dreamcast",
    "category": "Driving/Racing",
    "region": "USA",
    "release_year": "1999",
    "downloads": "1250",
    "download_url": "https://downloads.romspedia.com/roms/Hydro%20Thunder%20%28USA%29%20%28Rev%20A%29.7z"
  },
  {
    "title": "Jet Grind Radio",
    "slug": "jet-grind-radio",
    "page_url": "https://www.romspedia.com/roms/sega-dreamcast/jet-grind-radio",
    "image": "https://static.romspedia.com/webp/roms/jet-grind-radio-sega-dreamcast-cover.webp",
    "rating": "N/A",
    "file_name": "Jet Grind Radio (USA).7z",
    "size": "unknown",
    "console": "Dreamcast",
    "category": "Platform",
    "region": "USA",
    "release_year": "2000",
    "downloads": "1215",
    "download_url": "https://downloads.romspedia.com/roms/Jet%20Grind%20Radio%20%28USA%29.7z"
  },
  {
    "title": "King Of Fighters 2000 The (J)",
    "slug": "king-of-fighters-2000-the-j",
    "page_url": "https://www.romspedia.com/roms/sega-dreamcast/king-of-fighters-2000-the-j",
    "image": "https://static.romspedia.com/webp/roms/king-of-fighters-2000-the-dreamcast-cover-japan.webp",
    "rating": "N/A",
    "file_name": "King of Fighters 2000, The (Japan).7z",
    "size": "unknown",
    "console": "Dreamcast",
    "category": "Fighting",
    "region": "Japan",
    "release_year": "2002",
    "downloads": "963",
    "download_url": "https://downloads.romspedia.com/roms/King%20of%20Fighters%202000%2C%20The%20%28Japan%29.7z"
  },
  {
    "title": "Marvel Vs. Capcom Clash Of Super Heroes (J)",
    "slug": "marvel-vs-capcom-clash-of-super-heroes-j",
    "page_url": "https://www.romspedia.com/roms/sega-dreamcast/marvel-vs-capcom-clash-of-super-heroes-j",
    "image": "https://static.romspedia.com/webp/roms/marvel-vs-capcom-clash-of-super-heroes-sega-dreamcast-cover-japan.webp",
    "rating": "N/A",
    "file_name": "Marvel vs. Capcom - Clash of Super Heroes (Japan).7z",
    "size": "unknown",
    "console": "Dreamcast",
    "category": "Fight",
    "region": "Japan",
    "release_year": "1998",
    "downloads": "786",
    "download_url": "https://downloads.romspedia.com/roms/Marvel%20vs.%20Capcom%20-%20Clash%20of%20Super%20Heroes%20%28Japan%29.7z"
  },
  {
    "title": "Max Steel Covert Missions",
    "slug": "max-steel-covert-missions",
    "page_url": "https://www.romspedia.com/roms/sega-dreamcast/max-steel-covert-missions",
    "image": "https://static.romspedia.com/webp/roms/max-steel-covert-missions-dreamcast-cover.webp",
    "rating": "N/A",
    "file_name": "Max Steel - Covert Missions (USA).7z",
    "size": "unknown",
    "console": "Dreamcast",
    "category": "Action",
    "region": "USA",
    "release_year": "2001",
    "downloads": "880",
    "download_url": "https://downloads.romspedia.com/roms/Max%20Steel%20-%20Covert%20Missions%20%28USA%29.7z"
  },
  {
    "title": "NBA 2K",
    "slug": "nba-2k",
    "page_url": "https://www.romspedia.com/roms/sega-dreamcast/nba-2k",
    "image": "https://static.romspedia.com/webp/roms/nba-2k-dreamcast-cover.webp",
    "rating": "N/A",
    "file_name": "NBA 2K (USA).7z",
    "size": "unknown",
    "console": "Dreamcast",
    "category": "Sports",
    "region": "USA",
    "release_year": "2001",
    "downloads": "1296",
    "download_url": "https://downloads.romspedia.com/roms/NBA%202K%20%28USA%29.7z"
  },
  {
    "title": "NBA 2K1",
    "slug": "nba-2k1",
    "page_url": "https://www.romspedia.com/roms/sega-dreamcast/nba-2k1",
    "image": "https://static.romspedia.com/webp/roms/nba-2k1-dreamcast-cover.webp",
    "rating": "N/A",
    "file_name": "NBA 2K1 (USA).7z",
    "size": "unknown",
    "console": "Dreamcast",
    "category": "Sports",
    "region": "USA",
    "release_year": "2000",
    "downloads": "1102",
    "download_url": "https://downloads.romspedia.com/roms/NBA%202K1%20%28USA%29.7z"
  },
  {
    "title": "Phantasy Star Online",
    "slug": "phantasy-star-online",
    "page_url": "https://www.romspedia.com/roms/sega-dreamcast/phantasy-star-online",
    "image": "https://static.romspedia.com/webp/roms/phantasy-star-online-dreamcast-cover.webp",
    "rating": "N/A",
    "file_name": "Phantasy Star Online (USA) (En,Ja,Fr,De,Es) (Rev B).7z",
    "size": "unknown",
    "console": "Dreamcast",
    "category": "Role-Playing",
    "region": "USA",
    "release_year": "2000",
    "downloads": "1008",
    "download_url": "https://downloads.romspedia.com/roms/Phantasy%20Star%20Online%20%28USA%29%20%28En%2CJa%2CFr%2CDe%2CEs%29%20%28Rev%20B%29.7z"
  },
  {
    "title": "Prince Of Persia Arabian Nights",
    "slug": "prince-of-persia-arabian-nights",
    "page_url": "https://www.romspedia.com/roms/sega-dreamcast/prince-of-persia-arabian-nights",
    "image": "https://static.romspedia.com/webp/roms/prince-of-persia-arabian-nights-dreamcast-cover.webp",
    "rating": "N/A",
    "file_name": "Prince of Persia - Arabian Nights (USA).7z",
    "size": "unknown",
    "console": "Dreamcast",
    "category": "Platform",
    "region": "USA",
    "release_year": "1999",
    "downloads": "1527",
    "download_url": "https://downloads.romspedia.com/roms/Prince%20of%20Persia%20-%20Arabian%20Nights%20%28USA%29.7z"
  },
  {
    "title": "Quake III Arena",
    "slug": "quake-iii-arena",
    "page_url": "https://www.romspedia.com/roms/sega-dreamcast/quake-iii-arena",
    "image": "https://static.romspedia.com/webp/roms/quake-III-arena-dreamcast-cover.webp",
    "rating": "N/A",
    "file_name": "Quake III - Arena (USA).7z",
    "size": "unknown",
    "console": "Dreamcast",
    "category": "Shoot'em Up",
    "region": "USA",
    "release_year": "1999",
    "downloads": "1513",
    "download_url": "https://downloads.romspedia.com/roms/Quake%20III%20-%20Arena%20%28USA%29.7z"
  },
  {
    "title": "Re Volt",
    "slug": "re-volt",
    "page_url": "https://www.romspedia.com/roms/sega-dreamcast/re-volt",
    "image": "https://static.romspedia.com/webp/roms/re-volt-dreamcast-cover.webp",
    "rating": "N/A",
    "file_name": "Re-Volt (USA).7z",
    "size": "unknown",
    "console": "Dreamcast",
    "category": "Driving/Racing",
    "region": "USA",
    "release_year": "1999",
    "downloads": "1218",
    "download_url": "https://downloads.romspedia.com/roms/Re-Volt%20%28USA%29.7z"
  },
  {
    "title": "Record Of Lodoss War",
    "slug": "record-of-lodoss-war",
    "page_url": "https://www.romspedia.com/roms/sega-dreamcast/record-of-lodoss-war",
    "image": "https://static.romspedia.com/webp/roms/record-of-lodoss-war-dreamcast-cover.webp",
    "rating": "N/A",
    "file_name": "Record of Lodoss War (USA).7z",
    "size": "unknown",
    "console": "Dreamcast",
    "category": "Role-Playing",
    "region": "USA",
    "release_year": "2000",
    "downloads": "872",
    "download_url": "https://downloads.romspedia.com/roms/Record%20of%20Lodoss%20War%20%28USA%29.7z"
  },
  {
    "title": "Resident Evil 2 - Disc #1 (E)",
    "slug": "resident-evil-2-disc-1-e",
    "page_url": "https://www.romspedia.com/roms/sega-dreamcast/resident-evil-2-disc-1-e",
    "image": "https://static.romspedia.com/webp/roms/resident-evil-2-sega-dreamcast-cover-disc-1-europe.webp",
    "rating": "N/A",
    "file_name": "Resident Evil 2 (Europe) (En,Fr) (Disc 1).7z",
    "size": "unknown",
    "console": "Dreamcast",
    "category": "Survival",
    "region": "Europe",
    "release_year": "1998",
    "downloads": "895",
    "download_url": "https://downloads.romspedia.com/roms/Resident%20Evil%202%20%28Europe%29%20%28En%2CFr%29%20%28Disc%201%29.7z"
  },
  {
    "title": "Sega Rally 2 (J)",
    "slug": "sega-rally-2-j",
    "page_url": "https://www.romspedia.com/roms/sega-dreamcast/sega-rally-2-j",
    "image": "https://static.romspedia.com/webp/roms/sega-rally-2-dreamcast-cover-japan.webp",
    "rating": "N/A",
    "file_name": "Sega Rally 2 (Japan).7z",
    "size": "unknown",
    "console": "Dreamcast",
    "category": "Driving/Racing",
    "region": "Japan",
    "release_year": "1999",
    "downloads": "1273",
    "download_url": "https://downloads.romspedia.com/roms/Sega%20Rally%202%20%28Japan%29.7z"
  },
  {
    "title": "Sega Smash Pack Volume 1",
    "slug": "sega-smash-pack-volume-1",
    "page_url": "https://www.romspedia.com/roms/sega-dreamcast/sega-smash-pack-volume-1",
    "image": "https://static.romspedia.com/webp/roms/sega-smash-pack-volume-1-dreamcast-cover.webp",
    "rating": "N/A",
    "file_name": "Sega Smash Pack - Volume 1 (USA).7z",
    "size": "unknown",
    "console": "Dreamcast",
    "category": "Compilation",
    "region": "USA",
    "release_year": "2000",
    "downloads": "1379",
    "download_url": "https://downloads.romspedia.com/roms/Sega%20Smash%20Pack%20-%20Volume%201%20%28USA%29.7z"
  },
  {
    "title": "Shadow Man",
    "slug": "shadow-man",
    "page_url": "https://www.romspedia.com/roms/sega-dreamcast/shadow-man",
    "image": "https://static.romspedia.com/webp/roms/shadow-man-dreamcast-cover.webp",
    "rating": "N/A",
    "file_name": "Shadow Man (USA).7z",
    "size": "unknown",
    "console": "Dreamcast",
    "category": "Action",
    "region": "USA",
    "release_year": "1999",
    "downloads": "902",
    "download_url": "https://downloads.romspedia.com/roms/Shadow%20Man%20%28USA%29.7z"
  },
  {
    "title": "Shenmue - Disc #1",
    "slug": "shenmue-disc-1",
    "page_url": "https://www.romspedia.com/roms/sega-dreamcast/shenmue-disc-1",
    "image": "https://static.romspedia.com/webp/roms/shenmue-dreamcast-cover-disc-1.webp",
    "rating": "N/A",
    "file_name": "Shenmue (USA) (Disc 1).7z",
    "size": "unknown",
    "console": "Dreamcast",
    "category": "Role-Playing",
    "region": "USA",
    "release_year": "1999",
    "downloads": "1085",
    "download_url": "https://downloads.romspedia.com/roms/Shenmue%20%28USA%29%20%28Disc%201%29.7z"
  },
  {
    "title": "Shenmue - Disc #2",
    "slug": "shenmue-disc-2",
    "page_url": "https://www.romspedia.com/roms/sega-dreamcast/shenmue-disc-2",
    "image": "https://static.romspedia.com/webp/roms/shenmue-dreamcast-cover-disc-2.webp",
    "rating": "N/A",
    "file_name": "Shenmue (USA) (Disc 2).7z",
    "size": "unknown",
    "console": "Dreamcast",
    "category": "Action",
    "region": "USA",
    "release_year": "1999",
    "downloads": "838",
    "download_url": "https://downloads.romspedia.com/roms/Shenmue%20%28USA%29%20%28Disc%202%29.7z"
  },
  {
    "title": "Skies Of Arcadia - Disc #1",
    "slug": "skies-of-arcadia-disc-1",
    "page_url": "https://www.romspedia.com/roms/sega-dreamcast/skies-of-arcadia-disc-1",
    "image": "https://static.romspedia.com/webp/roms/skies-of-arcadia-dreamcast-cover-disc-1.webp",
    "rating": "N/A",
    "file_name": "Skies of Arcadia (USA) (Disc 1).7z",
    "size": "unknown",
    "console": "Dreamcast",
    "category": "Role-Playing",
    "region": "USA",
    "release_year": "2000",
    "downloads": "1328",
    "download_url": "https://downloads.romspedia.com/roms/Skies%20of%20Arcadia%20%28USA%29%20%28Disc%201%29.7z"
  },
  {
    "title": "Skies Of Arcadia - Disc #2",
    "slug": "skies-of-arcadia-disc-2",
    "page_url": "https://www.romspedia.com/roms/sega-dreamcast/skies-of-arcadia-disc-2",
    "image": "https://static.romspedia.com/webp/roms/skies-of-arcadia-dreamcast-cover-disc-2.webp",
    "rating": "N/A",
    "file_name": "Skies of Arcadia (USA) (Disc 2).7z",
    "size": "unknown",
    "console": "Dreamcast",
    "category": "Role-Playing",
    "region": "USA",
    "release_year": "2000",
    "downloads": "1032",
    "download_url": "https://downloads.romspedia.com/roms/Skies%20of%20Arcadia%20%28USA%29%20%28Disc%202%29.7z"
  },
  {
    "title": "Sonic Adventure 2 The Trial",
    "slug": "sonic-adventure-2-the-trial-usa",
    "page_url": "https://www.romspedia.com/roms/sega-dreamcast/sonic-adventure-2-the-trial-usa",
    "image": "https://static.romspedia.com/webp/roms/sonic-adventure-2-the-trial-dreamcast-cover.webp",
    "rating": "N/A",
    "file_name": "Sonic Adventure 2 - The Trial (USA, Japan) (En,Ja).7z",
    "size": "93.57MB",
    "console": "Dreamcast",
    "category": "Action",
    "region": "USA",
    "release_year": "2001",
    "downloads": "1446",
    "download_url": "https://downloads.romspedia.com/roms/Sonic Adventure 2 - The Trial (USA, Japan) (En,Ja).7z"
  },
  {
    "title": "Sonic Adventure International (J)",
    "slug": "sonic-adventure-international-jp",
    "page_url": "https://www.romspedia.com/roms/sega-dreamcast/sonic-adventure-international-jp",
    "image": "https://static.romspedia.com/webp/roms/sonic-adventure-international-dreamcast-cover-japan.webp",
    "rating": "N/A",
    "file_name": "Sonic Adventure International (Japan) (En,Ja,Fr,De,Es).7z",
    "size": "unknown",
    "console": "Dreamcast",
    "category": "Platform",
    "region": "Japan",
    "release_year": "1998",
    "downloads": "970",
    "download_url": "https://downloads.romspedia.com/roms/Sonic%20Adventure%20International%20%28Japan%29%20%28En%2CJa%2CFr%2CDe%2CEs%29.7z"
  },
  {
    "title": "Soulcalibur (J)",
    "slug": "soulcalibur-j",
    "page_url": "https://www.romspedia.com/roms/sega-dreamcast/soulcalibur-j",
    "image": "https://static.romspedia.com/webp/roms/soulcalibur-dreamcast-cover-japan.webp",
    "rating": "N/A",
    "file_name": "Soulcalibur (Japan).7z",
    "size": "unknown",
    "console": "Dreamcast",
    "category": "Fight",
    "region": "Japan",
    "release_year": "1999",
    "downloads": "1302",
    "download_url": "https://downloads.romspedia.com/roms/Soulcalibur%20%28Japan%29.7z"
  },
  {
    "title": "Space Channel 5",
    "slug": "space-channel-5",
    "page_url": "https://www.romspedia.com/roms/sega-dreamcast/space-channel-5",
    "image": "https://static.romspedia.com/webp/roms/space-channel-5-dreamcast-cover.webp",
    "rating": "N/A",
    "file_name": "Space Channel 5 (USA).7z",
    "size": "unknown",
    "console": "Dreamcast",
    "category": "Music",
    "region": "USA",
    "release_year": "2000",
    "downloads": "922",
    "download_url": "https://downloads.romspedia.com/roms/Space%20Channel%205%20%28USA%29.7z"
  },
  {
    "title": "Street Fighter III 3rd Strike Fight For The Future (J)",
    "slug": "street-fighter-iii-3rd-strike-fight-for-the-future-j",
    "page_url": "https://www.romspedia.com/roms/sega-dreamcast/street-fighter-iii-3rd-strike-fight-for-the-future-j",
    "image": "https://static.romspedia.com/webp/roms/street-fighter-III-3rd-strike-fight-for-the-future-dreamcast-cover-japan.webp",
    "rating": "N/A",
    "file_name": "Street Fighter III - 3rd Strike - Fight for the Future (Japan).7z",
    "size": "unknown",
    "console": "Dreamcast",
    "category": "Fight",
    "region": "USA",
    "release_year": "1999",
    "downloads": "924",
    "download_url": "https://downloads.romspedia.com/roms/Street%20Fighter%20III%20-%203rd%20Strike%20-%20Fight%20for%20the%20Future%20%28Japan%29.7z"
  },
  {
    "title": "Tennis 2K2",
    "slug": "tennis-2k2",
    "page_url": "https://www.romspedia.com/roms/sega-dreamcast/tennis-2k2",
    "image": "https://static.romspedia.com/webp/roms/tennis-2k2-dreamcast-cover.webp",
    "rating": "N/A",
    "file_name": "Tennis 2K2 (USA) (En,Ja,Fr,De,Es) (Rev A).7z",
    "size": "unknown",
    "console": "Dreamcast",
    "category": "Sports",
    "region": "USA",
    "release_year": "2001",
    "downloads": "1128",
    "download_url": "https://downloads.romspedia.com/roms/Tennis%202K2%20%28USA%29%20%28En%2CJa%2CFr%2CDe%2CEs%29%20%28Rev%20A%29.7z"
  },
  {
    "title": "The Typing of the Dead",
    "slug": "the-typing-of-the-dead",
    "page_url": "https://www.romspedia.com/roms/sega-dreamcast/the-typing-of-the-dead",
    "image": "https://static.romspedia.com/webp/roms/the-typing-of-the-dead-dreamcast-cover.webp",
    "rating": "N/A",
    "file_name": "Typing of the Dead, The.zip",
    "size": "unknown",
    "console": "Dreamcast",
    "category": "Survival horror",
    "region": "USA",
    "release_year": "1999",
    "downloads": "842",
    "download_url": "https://downloads.romspedia.com/roms/Typing%20of%20the%20Dead%2C%20The.zip"
  },
  {
    "title": "Toy Commander",
    "slug": "toy-commander",
    "page_url": "https://www.romspedia.com/roms/sega-dreamcast/toy-commander",
    "image": "https://static.romspedia.com/webp/roms/toy-commander-dreamcast-cover.webp",
    "rating": "N/A",
    "file_name": "Toy Commander (USA) (En,Fr,De,Es).7z",
    "size": "unknown",
    "console": "Dreamcast",
    "category": "Action",
    "region": "USA",
    "release_year": "1999",
    "downloads": "948",
    "download_url": "https://downloads.romspedia.com/roms/Toy%20Commander%20%28USA%29%20%28En%2CFr%2CDe%2CEs%29.7z"
  },
  {
    "title": "Unreal Tournament",
    "slug": "unreal-tournament",
    "page_url": "https://www.romspedia.com/roms/sega-dreamcast/unreal-tournament",
    "image": "https://static.romspedia.com/webp/roms/undreal-tournament-dreamcast-cover.webp",
    "rating": "N/A",
    "file_name": "Unreal Tournament (USA).7z",
    "size": "unknown",
    "console": "Dreamcast",
    "category": "Action",
    "region": "USA",
    "release_year": "1999",
    "downloads": "1315",
    "download_url": "https://downloads.romspedia.com/roms/Unreal%20Tournament%20%28USA%29.7z"
  },
  {
    "title": "Vigilante 8 2nd Offense",
    "slug": "vigilante-8-2nd-offense",
    "page_url": "https://www.romspedia.com/roms/sega-dreamcast/vigilante-8-2nd-offense",
    "image": "https://static.romspedia.com/webp/roms/viglante-8-2nd-offense-sega-dreamcast-cover.webp",
    "rating": "N/A",
    "file_name": "Vigilante 8 - 2nd Offense (USA).7z",
    "size": "unknown",
    "console": "Dreamcast",
    "category": "Vehicular combat",
    "region": "USA",
    "release_year": "1999",
    "downloads": "1353",
    "download_url": "https://downloads.romspedia.com/roms/Vigilante%208%20-%202nd%20Offense%20%28USA%29.7z"
  },
  {
    "title": "Virtua Fighter 3tb",
    "slug": "virtua-fighter-3tb",
    "page_url": "https://www.romspedia.com/roms/sega-dreamcast/virtua-fighter-3tb",
    "image": "https://static.romspedia.com/webp/roms/virtua-fighter-3tb-dreamcast-cover.webp",
    "rating": "N/A",
    "file_name": "Virtua Fighter 3tb (USA).7z",
    "size": "unknown",
    "console": "Dreamcast",
    "category": "Fight",
    "region": "USA",
    "release_year": "1999",
    "downloads": "1325",
    "download_url": "https://downloads.romspedia.com/roms/Virtua%20Fighter%203tb%20%28USA%29.7z"
  },
  {
    "title": "WWF Royal Rumble",
    "slug": "wwf-royal-rumble",
    "page_url": "https://www.romspedia.com/roms/sega-dreamcast/wwf-royal-rumble",
    "image": "https://static.romspedia.com/webp/roms/wwf-royal-rumble-dreamcast-cover.webp",
    "rating": "N/A",
    "file_name": "WWF Royal Rumble (USA).7z",
    "size": "unknown",
    "console": "Dreamcast",
    "category": "Sports",
    "region": "USA",
    "release_year": "N/A",
    "downloads": "1101",
    "download_url": "https://downloads.romspedia.com/roms/WWF%20Royal%20Rumble%20%28USA%29.7z"
  },
  {
    "title": "Zombie Revenge (J)",
    "slug": "zombie-revenge-j",
    "page_url": "https://www.romspedia.com/roms/sega-dreamcast/zombie-revenge-j",
    "image": "https://static.romspedia.com/webp/roms/zombie-revenge-dreamcast-cover-japan.webp",
    "rating": "N/A",
    "file_name": "Zombie Revenge (Japan).7z",
    "size": "unknown",
    "console": "Dreamcast",
    "category": "Beat 'em up",
    "region": "Japan",
    "release_year": "1999",
    "downloads": "1414",
    "download_url": "https://downloads.romspedia.com/roms/Zombie%20Revenge%20%28Japan%29.7z"
  },
  {
    "title": "D2 (Disc 1)",
    "slug": "d2-disc-1",
    "page_url": "https://www.romspedia.com/roms/sega-dreamcast/d2-disc-1",
    "image": "https://static.romspedia.com/webp/roms/d2-dreamcast-cover-disc-1.webp",
    "rating": "N/A",
    "file_name": "D2 (USA) (Disc 1).zip",
    "size": "unknown",
    "console": "Dreamcast",
    "category": "Survival horror",
    "region": "USA",
    "release_year": "2000",
    "downloads": "621",
    "download_url": "https://downloads.romspedia.com/roms/D2%20%28USA%29%20%28Disc%201%29.zip"
  },
  {
    "title": "D2 (Disc 2)",
    "slug": "d2-disc-2",
    "page_url": "https://www.romspedia.com/roms/sega-dreamcast/d2-disc-2",
    "image": "https://static.romspedia.com/webp/roms/d2-dreamcast-cover-disc-2.webp",
    "rating": "N/A",
    "file_name": "D2 (USA) (Disc 2).zip",
    "size": "unknown",
    "console": "Dreamcast",
    "category": "Survival horror",
    "region": "USA",
    "release_year": "2000",
    "downloads": "410",
    "download_url": "https://downloads.romspedia.com/roms/D2%20%28USA%29%20%28Disc%202%29.zip"
  },
  {
    "title": "D2 (Disc 3)",
    "slug": "d2-disc-3",
    "page_url": "https://www.romspedia.com/roms/sega-dreamcast/d2-disc-3",
    "image": "https://static.romspedia.com/webp/roms/d2-dreamcast-cover-disc-3.webp",
    "rating": "N/A",
    "file_name": "D2 (USA) (Disc 3).zip",
    "size": "unknown",
    "console": "Dreamcast",
    "category": "Survival horror",
    "region": "USA",
    "release_year": "2000",
    "downloads": "372",
    "download_url": "https://downloads.romspedia.com/roms/D2%20%28USA%29%20%28Disc%203%29.zip"
  },
  {
    "title": "D2 (Disc 4)",
    "slug": "d2-disc-4",
    "page_url": "https://www.romspedia.com/roms/sega-dreamcast/d2-disc-4",
    "image": "https://static.romspedia.com/webp/roms/d2-dreamcast-cover-disc-4.webp",
    "rating": "N/A",
    "file_name": "D2 (USA) (Disc 4).zip",
    "size": "unknown",
    "console": "Dreamcast",
    "category": "Survival horror",
    "region": "USA",
    "release_year": "2000",
    "downloads": "363",
    "download_url": "https://downloads.romspedia.com/roms/D2%20%28USA%29%20%28Disc%204%29.zip"
  },
  {
    "title": "Death Crimson OX",
    "slug": "death-crimson-ox",
    "page_url": "https://www.romspedia.com/roms/sega-dreamcast/death-crimson-ox",
    "image": "https://static.romspedia.com/webp/roms/death-crimson-ox-dreamcast-cover.webp",
    "rating": "N/A",
    "file_name": "Death Crimson OX (USA).7z",
    "size": "unknown",
    "console": "Dreamcast",
    "category": "Action",
    "region": "USA",
    "release_year": "2001",
    "downloads": "646",
    "download_url": "https://downloads.romspedia.com/roms/Death%20Crimson%20OX%20%28USA%29.7z"
  },
  {
    "title": "Evolution 2: Far Off Promise",
    "slug": "evolution-2-far-off-promise",
    "page_url": "https://www.romspedia.com/roms/sega-dreamcast/evolution-2-far-off-promise",
    "image": "https://static.romspedia.com/webp/roms/evolution-2-far-off-promise-dreamcast-cover.webp",
    "rating": "N/A",
    "file_name": "[GDI] Evolution 2 - Far Off Promise (US).7z",
    "size": "unknown",
    "console": "Dreamcast",
    "category": "N/A",
    "region": "USA",
    "release_year": "1999",
    "downloads": "460",
    "download_url": "https://downloads.romspedia.com/roms/%5BGDI%5D%20Evolution%202%20-%20Far%20Off%20Promise%20%28US%29.7z"
  },
  {
    "title": "NFL Blitz 2001 (USA)",
    "slug": "nfl-blitz-2001-usa",
    "page_url": "https://www.romspedia.com/roms/sega-dreamcast/nfl-blitz-2001-usa",
    "image": "https://static.romspedia.com/webp/roms/nfl-blitz-2001-dreamcast-cover.webp",
    "rating": "N/A",
    "file_name": "NFL Blitz 2001 v1.001 (2000)(Midway)(NTSC)(US)[!].zip",
    "size": "unknown",
    "console": "Dreamcast",
    "category": "Simulation",
    "region": "USA",
    "release_year": "2000",
    "downloads": "509",
    "download_url": "https://downloads.romspedia.com/roms/NFL%20Blitz%202001%20v1.001%20%282000%29%28Midway%29%28NTSC%29%28US%29%5B%21%5D.zip"
  },
  {
    "title": "NFL Blitz 2001 (USA)[ECHELON]",
    "slug": "nfl-blitz-2001-usa-echelon",
    "page_url": "https://www.romspedia.com/roms/sega-dreamcast/nfl-blitz-2001-usa-echelon",
    "image": "https://static.romspedia.com/webp/roms/nfl-blitz-2001-dreamcast-cover-ECHELON.webp",
    "rating": "N/A",
    "file_name": "NFL Blitz 2001 (US)[ECHELON].zip",
    "size": "unknown",
    "console": "Dreamcast",
    "category": "Simulation",
    "region": "USA",
    "release_year": "2000",
    "downloads": "699",
    "download_url": "https://downloads.romspedia.com/roms/NFL%20Blitz%202001%20%28US%29%5BECHELON%5D.zip"
  },
  {
    "title": "Seaman",
    "slug": "seaman",
    "page_url": "https://www.romspedia.com/roms/sega-dreamcast/seaman",
    "image": "https://static.romspedia.com/webp/roms/seaman-dreamcast-cover.webp",
    "rating": "N/A",
    "file_name": "Seaman (USA).7z",
    "size": "unknown",
    "console": "Dreamcast",
    "category": "Simulation",
    "region": "USA",
    "release_year": "2000",
    "downloads": "578",
    "download_url": "https://downloads.romspedia.com/roms/Seaman%20%28USA%29.7z"
  },
  {
    "title": "Seventh Cross Evolution",
    "slug": "seventh-cross-evolution",
    "page_url": "https://www.romspedia.com/roms/sega-dreamcast/seventh-cross-evolution",
    "image": "https://static.romspedia.com/webp/roms/seventh-cross-evolution-cover-dreamcast.webp",
    "rating": "N/A",
    "file_name": "seventh_cross_evolution_v1.000.zip",
    "size": "unknown",
    "console": "Dreamcast",
    "category": "Action",
    "region": "USA",
    "release_year": "N/A",
    "downloads": "506",
    "download_url": "https://downloads.romspedia.com/roms/seventh_cross_evolution_v1.000.zip"
  },
  {
    "title": "Shenmue - Disc #3",
    "slug": "shenmue-disc-3",
    "page_url": "https://www.romspedia.com/roms/sega-dreamcast/shenmue-disc-3",
    "image": "https://static.romspedia.com/webp/roms/shenmue-dreamcast-cover-disc-3.webp",
    "rating": "N/A",
    "file_name": "Shenmue (USA) (Disc 3).7z",
    "size": "unknown",
    "console": "Dreamcast",
    "category": "Action",
    "region": "USA",
    "release_year": "1999",
    "downloads": "755",
    "download_url": "https://downloads.romspedia.com/roms/Shenmue%20%28USA%29%20%28Disc%203%29.7z"
  },
  {
    "title": "Shenmue II - Disc #1 (J)",
    "slug": "shenmue-ii-disc-1-j",
    "page_url": "https://www.romspedia.com/roms/sega-dreamcast/shenmue-ii-disc-1-j",
    "image": "https://static.romspedia.com/webp/roms/shenmue-II-dreamcast-cover-disc-1-japan.webp",
    "rating": "N/A",
    "file_name": "Shenmue II (Japan) (Disc 1).7z",
    "size": "unknown",
    "console": "Dreamcast",
    "category": "Role-Playing",
    "region": "Japan",
    "release_year": "2001",
    "downloads": "492",
    "download_url": "https://downloads.romspedia.com/roms/Shenmue%20II%20%28Japan%29%20%28Disc%201%29.7z"
  },
  {
    "title": "South Park Chef's Luv Shack",
    "slug": "south-park-chefs-luv-shack",
    "page_url": "https://www.romspedia.com/roms/sega-dreamcast/south-park-chefs-luv-shack",
    "image": "https://static.romspedia.com/webp/roms/south-park-chefs-luv-shack-dreamcast-cover.webp",
    "rating": "N/A",
    "file_name": "South Park - Chefs Luv Shack (USA).7z",
    "size": "unknown",
    "console": "Dreamcast",
    "category": "Party",
    "region": "USA",
    "release_year": "1999",
    "downloads": "612",
    "download_url": "https://downloads.romspedia.com/roms/South%20Park%20-%20Chefs%20Luv%20Shack%20%28USA%29.7z"
  },
  {
    "title": "Tech Romancer",
    "slug": "tech-romancer",
    "page_url": "https://www.romspedia.com/roms/sega-dreamcast/tech-romancer",
    "image": "https://static.romspedia.com/webp/roms/tech-romancer-dreamcast-cover.webp",
    "rating": "N/A",
    "file_name": "Tech Romancer.zip",
    "size": "unknown",
    "console": "Dreamcast",
    "category": "Fighting",
    "region": "USA",
    "release_year": "1998",
    "downloads": "635",
    "download_url": "https://downloads.romspedia.com/roms/Tech%20Romancer.zip"
  }
]